{
 "cells": [
  {
   "cell_type": "code",
   "execution_count": 1,
   "metadata": {
    "collapsed": true
   },
   "outputs": [],
   "source": [
    "b =6\n",
    "def f2(a):\n",
    "    print(a)\n",
    "    print(b)\n",
    "    b=9"
   ]
  },
  {
   "cell_type": "code",
   "execution_count": 2,
   "outputs": [
    {
     "name": "stdout",
     "output_type": "stream",
     "text": [
      "3\n"
     ]
    },
    {
     "ename": "UnboundLocalError",
     "evalue": "local variable 'b' referenced before assignment",
     "output_type": "error",
     "traceback": [
      "\u001B[1;31m---------------------------------------------------------------------------\u001B[0m",
      "\u001B[1;31mUnboundLocalError\u001B[0m                         Traceback (most recent call last)",
      "\u001B[1;32m~\\AppData\\Local\\Temp/ipykernel_17180/3711521367.py\u001B[0m in \u001B[0;36m<module>\u001B[1;34m\u001B[0m\n\u001B[1;32m----> 1\u001B[1;33m \u001B[0mf2\u001B[0m\u001B[1;33m(\u001B[0m\u001B[1;36m3\u001B[0m\u001B[1;33m)\u001B[0m\u001B[1;33m\u001B[0m\u001B[1;33m\u001B[0m\u001B[0m\n\u001B[0m",
      "\u001B[1;32m~\\AppData\\Local\\Temp/ipykernel_17180/1208855470.py\u001B[0m in \u001B[0;36mf2\u001B[1;34m(a)\u001B[0m\n\u001B[0;32m      2\u001B[0m \u001B[1;32mdef\u001B[0m \u001B[0mf2\u001B[0m\u001B[1;33m(\u001B[0m\u001B[0ma\u001B[0m\u001B[1;33m)\u001B[0m\u001B[1;33m:\u001B[0m\u001B[1;33m\u001B[0m\u001B[1;33m\u001B[0m\u001B[0m\n\u001B[0;32m      3\u001B[0m     \u001B[0mprint\u001B[0m\u001B[1;33m(\u001B[0m\u001B[0ma\u001B[0m\u001B[1;33m)\u001B[0m\u001B[1;33m\u001B[0m\u001B[1;33m\u001B[0m\u001B[0m\n\u001B[1;32m----> 4\u001B[1;33m     \u001B[0mprint\u001B[0m\u001B[1;33m(\u001B[0m\u001B[0mb\u001B[0m\u001B[1;33m)\u001B[0m\u001B[1;33m\u001B[0m\u001B[1;33m\u001B[0m\u001B[0m\n\u001B[0m\u001B[0;32m      5\u001B[0m     \u001B[0mb\u001B[0m\u001B[1;33m=\u001B[0m\u001B[1;36m9\u001B[0m\u001B[1;33m\u001B[0m\u001B[1;33m\u001B[0m\u001B[0m\n",
      "\u001B[1;31mUnboundLocalError\u001B[0m: local variable 'b' referenced before assignment"
     ]
    }
   ],
   "source": [
    "f2(3)"
   ],
   "metadata": {
    "collapsed": false,
    "pycharm": {
     "name": "#%%\n"
    }
   }
  },
  {
   "cell_type": "code",
   "execution_count": 3,
   "outputs": [
    {
     "name": "stdout",
     "output_type": "stream",
     "text": [
      "  3           0 LOAD_GLOBAL              0 (print)\n",
      "              2 LOAD_FAST                0 (a)\n",
      "              4 CALL_FUNCTION            1\n",
      "              6 POP_TOP\n",
      "\n",
      "  4           8 LOAD_GLOBAL              0 (print)\n",
      "             10 LOAD_FAST                1 (b)\n",
      "             12 CALL_FUNCTION            1\n",
      "             14 POP_TOP\n",
      "\n",
      "  5          16 LOAD_CONST               1 (9)\n",
      "             18 STORE_FAST               1 (b)\n",
      "             20 LOAD_CONST               0 (None)\n",
      "             22 RETURN_VALUE\n"
     ]
    }
   ],
   "source": [
    "from dis import dis\n",
    "dis(f2)"
   ],
   "metadata": {
    "collapsed": false,
    "pycharm": {
     "name": "#%%\n"
    }
   }
  },
  {
   "cell_type": "code",
   "execution_count": null,
   "outputs": [],
   "source": [],
   "metadata": {
    "collapsed": false,
    "pycharm": {
     "name": "#%%\n"
    }
   }
  }
 ],
 "metadata": {
  "kernelspec": {
   "display_name": "Python 3",
   "language": "python",
   "name": "python3"
  },
  "language_info": {
   "codemirror_mode": {
    "name": "ipython",
    "version": 2
   },
   "file_extension": ".py",
   "mimetype": "text/x-python",
   "name": "python",
   "nbconvert_exporter": "python",
   "pygments_lexer": "ipython2",
   "version": "2.7.6"
  }
 },
 "nbformat": 4,
 "nbformat_minor": 0
}